{"layout":{"bloks_payload":{"data":[],"props":[{"id":"1386313794820768429","name":"ttrc_instance_id"}],"error_attribution":{"logging_id":"{\"callsite\":\"{\\\"product\\\":\\\"caa_reg\\\",\\\"feature\\\":\\\"com.bloks.www.bloks.caa.reg.username.async\\\",\\\"integration\\\":\\\"bloks_screen\\\",\\\"oncall\\\":\\\"caa_acquisition\\\"}\",\"push_phase\":\"C3\",\"version\":1,\"request_id\":\"A51E8GfW89EKnFeluRUyAMv\"}","source_map_id":"dUKEuzqN"},"tree":{"㐟":{"#":" (bk.action.core.Match, (bk.action.f32.Eq, (bk.action.bloks.GetVariable2, \"12fyicawyk\"), \"ertmadni_11\"), (bk.action.array.Make, (bk.action.core.Pattern, (bk.action.bool.Const, true), (bk.action.core.FuncConst, (bk.action.core.TakeLast, (bk.action.bloks.WriteGlobalConsistencyStore, \"CAA_REG_USERNAME:error_message:0\", \"\"), (bk.action.bloks.WriteGlobalConsistencyStore, \"CAA_REG_USERNAME:validation_state:0\", \"success\"), (bk.action.logging.LogEvent, \"caa_acquisition_client_ig_event\", \"\", (bk.action.map.Make, (bk.action.array.Make, \"core\", \"acquisition_client_params\"), (bk.action.array.Make, (bk.action.map.Make, (bk.action.array.Make, \"event\", \"event_category\", \"event_flow\", \"event_request_id\", \"event_step\", \"is_dark_mode\", \"exception_code\", \"exception_message\", \"exception_type\", \"extra_client_data\", \"logged_out_identifier\", \"logged_in_identifier\", \"waterfall_id\", \"reduction_push_phase\", \"reduction_region\"), (bk.action.array.Make, \"registration_flow_state\", \"registration_funnel\", \"ntf\", \"3df16f69-f433-4320-8c17-cd3b6edf4fd8\", \"username\", (ig.action.IsDarkModeEnabled), (bk.action.i32.Const, 0), \"\", \"\", (bk.action.mins.CallRuntime, 6), \"\", \"\", \"5f4ca58c-23a3-411a-8a8b-b46b40d8a0c2\", \"C3\", \"ireland\")), (bk.action.map.Make, (bk.action.array.Make, \"state\", \"entry_point\", \"reg_instance\", \"created_userid\", \"registration_flow_id\", \"youth_regulation_enabled\", \"notif_medium\", \"regulation_jurisdiction\"), (bk.action.array.Make, \"username_check_success\", null, \"f333aeae-9c6c-447d-8a3d-d323cf4e13b4\", null, \"68a3916b-4066-4466-b064-a39dbf3266e2\", (bk.action.bool.Const, false), null, null))))))))), (bk.action.core.Default, (bk.action.core.FuncConst, (bk.action.i32.Const, 1))))"}}}},"status":"ok"}